Workbook

Sheet Revenue_Drivers
A1: Scenario | B1: Base
A3: Assumptions by Scenario
A4: Metric | B4: Base | C4: Upside | D4: Downside
A5: Growth % | B5: 0.04 | C5: 0.05 | D5: 0.03
A6: Churn % | B6: 0.02 | C6: 0.015 | D6: 0.03
A7: S&M% | B7: 0.35 | C7: 0.32 | D7: 0.4
A8: R&D% | B8: 0.2 | C8: 0.18 | D8: 0.22
A9: G&A% | B9: 0.15 | C9: 0.14 | D9: 0.16
A10: CapEx% | B10: 0.03 | C10: 0.025 | D10: 0.04
A12: Active Assumptions
A13: Active Growth % | B13: {=INDEX(B5:D5, MATCH($B$1, B4:D4, 0))} -> 0.04
A14: Active Churn % | B14: {=INDEX(B6:D6, MATCH($B$1, B4:D4, 0))} -> 0.02
A15: Active S&M % | B15: {=INDEX(B7:D7, MATCH($B$1, B4:D4, 0))} -> 0.35
A16: Active R&D % | B16: {=INDEX(B8:D8, MATCH($B$1, B4:D4, 0))} -> 0.2
A17: Active G&A % | B17: {=INDEX(B9:D9, MATCH($B$1, B4:D4, 0))} -> 0.15
A18: Active CapEx % | B18: {=INDEX(B10:D10, MATCH($B$1, B4:D4, 0))} -> 0.03
A20: Assumptions
A21: Monthly Churn % | B21: =B14 -> 0.02
A22: Monthly New Customer Growth % | B22: =B13 -> 0.04
B23: 46023 | C23: =EDATE(B23,1) -> 46054 | D23: =EDATE(C23,1) -> 46082 | E23: =EDATE(D23,1) -> 46113 | F23: =EDATE(E23,1) -> 46143 | G23: =EDATE(F23,1) -> 46174 | H23: =EDATE(G23,1) -> 46204 | I23: =EDATE(H23,1) -> 46235 | J23: =EDATE(I23,1) -> 46266 | ... AK23: =EDATE(AJ23,1) -> 47088
A25: Customer Drivers
A26: Beginning Cusotmers | B26: 1000 | C26: =B29 -> 1020 | D26: =C29 -> 1040.6 | E26: =D29 -> 1061.788 | F26: =E29 -> 1082.5522 | G26: =F29 -> 1103.9012 | H26: =G29 -> 1125.8232 | I26: =H29 -> 1148.3067 | J26: =I29 -> 1171.3406 | ... AK26: =AJ29 -> 1999.7257
A27: New Customers | B27: =ROUND(B26*$B$22,0) -> 40 | C27: =ROUND(C26*$B$22,0) -> 41 | D27: =ROUND(D26*$B$22,0) -> 42 | E27: =ROUND(E26*$B$22,0) -> 42 | F27: =ROUND(F26*$B$22,0) -> 43 | G27: =ROUND(G26*$B$22,0) -> 44 | H27: =ROUND(H26*$B$22,0) -> 45 | I27: =ROUND(I26*$B$22,0) -> 46 | ... AK27: =ROUND(AK26*$B$22,0) -> 80
A28: Churned Customers | B28: =-B26*$B$21 -> -20 | C28: =-C26*$B$21 -> -20.4 | D28: =-D26*$B$21 -> -20.812 | E28: =-E26*$B$21 -> -21.23576 | F28: =-F26*$B$21 -> -21.651045 | G28: =-G26*$B$21 -> -22.078024 | H28: =-H26*$B$21 -> -22.516463 | I28: =-I26*$B$21 -> -22.966134 | ... AK28: =-AK26*$B$21 -> -39.994513
A29: Ending Customers | B29: =B26+B27+B28 -> 1020 | C29: =C26+C27+C28 -> 1040.6 | D29: =D26+D27+D28 -> 1061.788 | E29: =E26+E27+E28 -> 1082.5522 | F29: =F26+F27+F28 -> 1103.9012 | G29: =G26+G27+G28 -> 1125.8232 | H29: =H26+H27+H28 -> 1148.3067 | I29: =I26+I27+I28 -> 1171.3406 | ... AK29: =AK26+AK27+AK28 -> 2039.7312
A31: Pricing & Revenue Drivers
A32: Monthly ARPU ($) | B32: 120 | C32: 120 | D32: 120 | E32: 120 | F32: 120 | G32: 120 | H32: 120 | I32: 120 | J32: 120 | K32: 120 | L32: 120 | M32: 120 | N32: 120 | O32: 120 | P32: 120 | Q32: 120 | R32: 120 | S32: 120 | T32: 120 | U32: 120 | V32: 120 | W32: 120 | X32: 120 | Y32: 120 | Z32: 120 | AA32: 120 | AB32: 120 | AC32: 120 | AD32: 120 | AE32: 120 | AF32: 120 | AG32: 120 | AH32: 120 | AI32: 120 | AJ32: 120 | AK32: 120
A33: Expansion Rate (%) | B33: 0.005 | C33: 0.005 | D33: 0.005 | E33: 0.005 | F33: 0.005 | G33: 0.005 | H33: 0.005 | I33: 0.005 | J33: 0.005 | K33: 0.005 | L33: 0.005 | M33: 0.005 | N33: 0.005 | O33: 0.005 | P33: 0.005 | Q33: 0.005 | R33: 0.005 | S33: 0.005 | T33: 0.005 | U33: 0.005 | V33: 0.005 | W33: 0.005 | X33: 0.005 | Y33: 0.005 | Z33: 0.005 | AA33: 0.005 | AB33: 0.005 | AC33: 0.005 | AD33: 0.005 | AE33: 0.005 | AF33: 0.005 | AG33: 0.005 | AH33: 0.005 | AI33: 0.005 | AJ33: 0.005 | AK33: 0.005
A35: Calculated Outputs (Locked)
A36: Gross MRR | B36: =B29*B32 -> 122400 | C36: =C29*C32 -> 124872 | D36: =D29*D32 -> 127414.56 | E36: =E29*E32 -> 129906.27 | F36: =F29*F32 -> 132468.14 | G36: =G29*G32 -> 135098.78 | H36: =H29*H32 -> 137796.8 | I36: =I29*I32 -> 140560.87 | ... AK36: =AK29*AK32 -> 244767.74
A37: Expansion MRR | B37: =B36*B33 -> 612 | C37: =C36*C33 -> 624.36 | D37: =D36*D33 -> 637.0728 | E37: =E36*E33 -> 649.53134 | F37: =F36*F33 -> 662.34072 | G37: =G36*G33 -> 675.4939 | H37: =H36*H33 -> 688.98402 | I37: =I36*I33 -> 702.80434 | ... AK37: =AK36*AK33 -> 1223.8387
A38: Total MRR | B38: =B36+B37 -> 123012 | C38: =C36+C37 -> 125496.36 | D38: =D36+D37 -> 128051.63 | E38: =E36+E37 -> 130555.8 | F38: =F36+F37 -> 133130.48 | G38: =G36+G37 -> 135774.27 | H38: =H36+H37 -> 138485.79 | I38: =I36+I37 -> 141263.67 | ... AK38: =AK36+AK37 -> 245991.58
A39: Total ARR | B39: =B38*12 -> 1476144 | C39: =C38*12 -> 1505956.3 | D39: =D38*12 -> 1536619.6 | E39: =E38*12 -> 1566669.6 | F39: =F38*12 -> 1597565.8 | G39: =G38*12 -> 1629291.3 | H39: =H38*12 -> 1661829.5 | I39: =I38*12 -> 1695164.1 | ... AK39: =AK38*12 -> 2951898.9

Sheet Income_Statment 
A1: Assumptions
A2: Cost of Revenue % | B2: 0.25
A3: S&M % of Revenue | B3: =Revenue_Drivers!B15 -> 0.35
A4: R&D % of Revenue | B4: =Revenue_Drivers!B16 -> 0.2
A5: G&A % of Revenue | B5: =Revenue_Drivers!B17 -> 0.15
B6: 46023 | C6: =EDATE(B6,1) -> 46054 | D6: =EDATE(C6,1) -> 46082 | E6: =EDATE(D6,1) -> 46113 | F6: =EDATE(E6,1) -> 46143 | G6: =EDATE(F6,1) -> 46174 | H6: =EDATE(G6,1) -> 46204 | I6: =EDATE(H6,1) -> 46235 | J6: =EDATE(I6,1) -> 46266 | ... AK6: =EDATE(AJ6,1) -> 47088
A9: Revenue | B9: =Revenue_Drivers!B38 -> 123012 | C9: =Revenue_Drivers!C38 -> 125496.36 | D9: =Revenue_Drivers!D38 -> 128051.63 | E9: =Revenue_Drivers!E38 -> 130555.8 | F9: =Revenue_Drivers!F38 -> 133130.48 | G9: =Revenue_Drivers!G38 -> 135774.27 | H9: =Revenue_Drivers!H38 -> 138485.79 | I9: =Revenue_Drivers!I38 -> 141263.67 | ... AK9: =Revenue_Drivers!AK38 -> 245991.58
A10: Cost of Revenue | B10: =-B9*$B$2 -> -30753 | C10: =-C9*$B$2 -> -31374.09 | D10: =-D9*$B$2 -> -32012.908 | E10: =-E9*$B$2 -> -32638.95 | F10: =-F9*$B$2 -> -33282.621 | G10: =-G9*$B$2 -> -33943.569 | H10: =-H9*$B$2 -> -34621.447 | I10: =-I9*$B$2 -> -35315.918 | ... AK10: =-AK9*$B$2 -> -61497.894
A11: Gross Profit | B11: =B9+B10 -> 92259 | C11: =C9+C10 -> 94122.27 | D11: =D9+D10 -> 96038.725 | E11: =E9+E10 -> 97916.85 | F11: =F9+F10 -> 99847.863 | G11: =G9+G10 -> 101830.71 | H11: =H9+H10 -> 103864.34 | I11: =I9+I10 -> 105947.75 | ... AK11: =AK9+AK10 -> 184493.68
A12: Gross Margin % | B12: =B11/B9 -> 0.75 | C12: =C11/C9 -> 0.75 | D12: =D11/D9 -> 0.75 | E12: =E11/E9 -> 0.75 | F12: =F11/F9 -> 0.75 | G12: =G11/G9 -> 0.75 | H12: =H11/H9 -> 0.75 | I12: =I11/I9 -> 0.75 | ... AK12: =AK11/AK9 -> 0.75
A14: Operating Expenses
A15: Sales & Marketing | B15: =-B9 * Revenue_Drivers!$B$15 -> -43054.2 | C15: =-C9 * Revenue_Drivers!$B$15 -> -43923.726 | D15: =-D9 * Revenue_Drivers!$B$15 -> -44818.071 | E15: =-E9 * Revenue_Drivers!$B$15 -> -45694.53 | F15: =-F9 * Revenue_Drivers!$B$15 -> -46595.669 | G15: =-G9 * Revenue_Drivers!$B$15 -> -47520.996 | H15: =-H9 * Revenue_Drivers!$B$15 -> -48470.026 | I15: =-I9 * Revenue_Drivers!$B$15 -> -49442.286 | ... AK15: =-AK9 * Revenue_Drivers!$B$15 -> -86097.052
A16: R&D | B16: =-B9 * Revenue_Drivers!$B$16 -> -24602.4 | C16: =-C9 * Revenue_Drivers!$B$16 -> -25099.272 | D16: =-D9 * Revenue_Drivers!$B$16 -> -25610.327 | E16: =-E9 * Revenue_Drivers!$B$16 -> -26111.16 | F16: =-F9 * Revenue_Drivers!$B$16 -> -26626.097 | G16: =-G9 * Revenue_Drivers!$B$16 -> -27154.855 | H16: =-H9 * Revenue_Drivers!$B$16 -> -27697.158 | I16: =-I9 * Revenue_Drivers!$B$16 -> -28252.735 | ... AK16: =-AK9 * Revenue_Drivers!$B$16 -> -49198.315
A17: General & Administrative | B17: =-B9 * Revenue_Drivers!$B$17 -> -18451.8 | C17: =-C9 * Revenue_Drivers!$B$17 -> -18824.454 | D17: =-D9 * Revenue_Drivers!$B$17 -> -19207.745 | E17: =-E9 * Revenue_Drivers!$B$17 -> -19583.37 | F17: =-F9 * Revenue_Drivers!$B$17 -> -19969.573 | G17: =-G9 * Revenue_Drivers!$B$17 -> -20366.141 | H17: =-H9 * Revenue_Drivers!$B$17 -> -20772.868 | I17: =-I9 * Revenue_Drivers!$B$17 -> -21189.551 | ... AK17: =-AK9 * Revenue_Drivers!$B$17 -> -36898.737
A18: Total OpEx | B18: =SUM(B15:B17) -> -86108.4 | C18: =SUM(C15:C17) -> -87847.452 | D18: =SUM(D15:D17) -> -89636.143 | E18: =SUM(E15:E17) -> -91389.06 | F18: =SUM(F15:F17) -> -93191.339 | G18: =SUM(G15:G17) -> -95041.992 | H18: =SUM(H15:H17) -> -96940.052 | I18: =SUM(I15:I17) -> -98884.571 | ... AK18: =SUM(AK15:AK17) -> -172194.1
A20: EBTIDA | B20: =B11+B18 -> 6150.6 | C20: =C11+C18 -> 6274.818 | D20: =D11+D18 -> 6402.5816 | E20: =E11+E18 -> 6527.79 | F20: =F11+F18 -> 6656.5242 | G20: =G11+G18 -> 6788.7137 | H20: =H11+H18 -> 6924.2894 | I20: =I11+I18 -> 7063.1837 | ... AK20: =AK11+AK18 -> 12299.579

Sheet Cash_Flow 
A1: Assumptions
A2: CapEx % of Revenue | B2: =Revenue_Drivers!B18 -> 0.03
B3: 46023 | C3: =EDATE(B3,1) -> 46054 | D3: =EDATE(C3,1) -> 46082 | E3: =EDATE(D3,1) -> 46113 | F3: =EDATE(E3,1) -> 46143 | G3: =EDATE(F3,1) -> 46174 | H3: =EDATE(G3,1) -> 46204 | I3: =EDATE(H3,1) -> 46235 | J3: =EDATE(I3,1) -> 46266 | ... AK3: =EDATE(AJ3,1) -> 47088
A4: Liquidity & Runway Metrics
A5: Avg Monthly Net Cash Flow | B5: =AVERAGE(B22:M22) -> 2749.8084
A6: Current Cash Balance | B6: =AK24 -> 2127964.3
A7: Monthly Burn | B7: =IF(B5<0,-B5,0) -> 0
A8: Months of Runway | B8: =IF(B7>0,B6/B7,"Cash Generative") -> Cash Generative
A10: Cash Flow from Operations
A11: EBTIDA | B11: ='Income_Statment '!B20 -> 6150.6 | C11: ='Income_Statment '!C20 -> 6274.818 | D11: ='Income_Statment '!D20 -> 6402.5816 | E11: ='Income_Statment '!E20 -> 6527.79 | F11: ='Income_Statment '!F20 -> 6656.5242 | G11: ='Income_Statment '!G20 -> 6788.7137 | H11: ='Income_Statment '!H20 -> 6924.2894 | I11: ='Income_Statment '!I20 -> 7063.1837 | ... AK11: ='Income_Statment '!AK20 -> 12299.579
A12: Change in Working Capital | B12: 0 | C12: 0 | D12: 0 | E12: 0 | F12: 0 | G12: 0 | H12: 0 | I12: 0 | J12: 0 | K12: 0 | L12: 0 | M12: 0 | N12: 0 | O12: 0 | P12: 0 | Q12: 0 | R12: 0 | S12: 0 | T12: 0 | U12: 0 | V12: 0 | W12: 0 | X12: 0 | Y12: 0 | Z12: 0 | AA12: 0 | AB12: 0 | AC12: 0 | AD12: 0 | AE12: 0 | AF12: 0 | AG12: 0 | AH12: 0 | AI12: 0 | AJ12: 0 | AK12: 0
A13: Operating Cash Flow | B13: =B11+B12 -> 6150.6 | C13: =C11+C12 -> 6274.818 | D13: =D11+D12 -> 6402.5816 | E13: =E11+E12 -> 6527.79 | F13: =F11+F12 -> 6656.5242 | G13: =G11+G12 -> 6788.7137 | H13: =H11+H12 -> 6924.2894 | I13: =I11+I12 -> 7063.1837 | ... AK13: =AK11+AK12 -> 12299.579
A15: Cash Flow from Investing
A16: Capital Expenditures | B16: =-'Income_Statment '!B9* Revenue_Drivers!$B$18 -> -3690.36 | C16: =-'Income_Statment '!C9* Revenue_Drivers!$B$18 -> -3764.8908 | D16: =-'Income_Statment '!D9* Revenue_Drivers!$B$18 -> -3841.549 | E16: =-'Income_Statment '!E9* Revenue_Drivers!$B$18 -> -3916.674 | F16: =-'Income_Statment '!F9* Revenue_Drivers!$B$18 -> -3993.9145 | G16: =-'Income_Statment '!G9* Revenue_Drivers!$B$18 -> -4073.2282 | H16: =-'Income_Statment '!H9* Revenue_Drivers!$B$18 -> -4154.5737 | I16: =-'Income_Statment '!I9* Revenue_Drivers!$B$18 -> -4237.9102 | ... AK16: =-'Income_Statment '!AK9* Revenue_Drivers!$B$18 -> -7379.7473
A17: Investing Cash Flow | B17: =B16 -> -3690.36 | C17: =C16 -> -3764.8908 | D17: =D16 -> -3841.549 | E17: =E16 -> -3916.674 | F17: =F16 -> -3993.9145 | G17: =G16 -> -4073.2282 | H17: =H16 -> -4154.5737 | I17: =I16 -> -4237.9102 | ... AK17: =AK16 -> -7379.7473
A19: Cash Flow from Financing
A20: Financing Cash Flow | B20: 0 | C20: 0 | D20: 0 | E20: 0 | F20: 0 | G20: 0 | H20: 0 | I20: 0 | J20: 0 | K20: 0 | L20: 0 | M20: 0 | N20: 0 | O20: 0 | P20: 0 | Q20: 0 | R20: 0 | S20: 0 | T20: 0 | U20: 0 | V20: 0 | W20: 0 | X20: 0 | Y20: 0 | Z20: 0 | AA20: 0 | AB20: 0 | AC20: 0 | AD20: 0 | AE20: 0 | AF20: 0 | AG20: 0 | AH20: 0 | AI20: 0 | AJ20: 0 | AK20: 0
A22: Net Cash Flow | B22: =B13+B17+B20 -> 2460.24 | C22: =C13+C17+C20 -> 2509.9272 | D22: =D13+D17+D20 -> 2561.0327 | E22: =E13+E17+E20 -> 2611.116 | F22: =F13+F17+F20 -> 2662.6097 | G22: =G13+G17+G20 -> 2715.4855 | H22: =H13+H17+H20 -> 2769.7158 | I22: =I13+I17+I20 -> 2825.2735 | ... AK22: =AK13+AK17+AK20 -> 4919.8315
A23: Beginning Cash | B23: 2000000 | C23: =B24 -> 2002460.2 | D23: =C24 -> 2004970.2 | E23: =D24 -> 2007531.2 | F23: =E24 -> 2010142.3 | G23: =F24 -> 2012804.9 | H23: =G24 -> 2015520.4 | I23: =H24 -> 2018290.1 | J23: =I24 -> 2021115.4 | ... AK23: =AJ24 -> 2123044.4
A24: Ending Cash | B24: =B22+B23 -> 2002460.2 | C24: =C22+C23 -> 2004970.2 | D24: =D22+D23 -> 2007531.2 | E24: =E22+E23 -> 2010142.3 | F24: =F22+F23 -> 2012804.9 | G24: =G22+G23 -> 2015520.4 | H24: =H22+H23 -> 2018290.1 | I24: =I22+I23 -> 2021115.4 | ... AK24: =AK22+AK23 -> 2127964.3
